mux2/mux2.v
`timescale 1ns/1ps

module mux2(a0,a1,s,y);

input s, a0, a1;
output y;
reg y;


always @ (a0 or a1 or s) begin
  case (s)
    1'b0: y = a0;
    1'b1: y = a1;
  endcase
end
endmodule
//

mux8/mux8.v
`include "../mux2/mux2.v"
`timescale 1ns / 1ps


module mux8(a0,a1,a2,a3,a4,a5,a6,a7,s0,s1,s2,y);
input a0,a1,a2,a3,a4,a5,a6,a7,s0,s1,s2;
output y;
wire w1,w2,w3,w4,w5,w6;

mux2 m0(a0,a1,s0,w1);
mux2 m1(a2,a3,s0,w2);
mux2 m2(a4,a5,s0,w3);
mux2 m3(a6,a7,s0,w4);

mux2 m4(w1,w2,s1,w5);
mux2 m5(w3,w4,s1,w6);

mux2 m6(w5,w6,s2,y);

endmodule

mux8/mux8_tb.v
`timescale 1ns / 1ps

module mux8_tb();

reg a0,a1,a2,a3,a4,a5,a6,a7,s0,s1,s2;
wire y;

mux8 m0(a0,a1,a2,a3,a4,a5,a6,a7,s0,s1,s2,y);

initial begin
  $dumpfile("mux8_tb.vcd");
  $dumpvars(0,mux8_tb);
  $monitor("a0=%b a1=%b a2=%b a3=%b a4=%b a5=%b a6=%b a7=%b s0=%b s1=%b s2=%b y=%b",a0,a1,a2,a3,a4,a5,a6,a7,s0,s1,s2,y);
  a0 = 0; a1 = 0; a2 = 0; a3 = 0; a4 = 0; a5 = 0; a6 = 0; a7 = 0; s0 = 0; s1 = 0; s2 = 0;
  #10 a0=0; a1=0; a2=0; a3=0; a4=0; a5=0; a6=0; a7=0; s0=0; s1=0; s2=0;
  #10 a0=0; a1=0; a2=0; a3=0; a4=0; a5=0; a6=0; a7=0; s0=0; s1=0; s2=1;
  #10 a0=0; a1=0; a2=0; a3=0; a4=0; a5=0; a6=0; a7=0; s0=0; s1=1; s2=0;
  #10 a0=0; a1=0; a2=0; a3=0; a4=0; a5=0; a6=0; a7=0; s0=0; s1=1; s2=1;
  #10 a0=0; a1=0; a2=0; a3=0; a4=0; a5=0; a6=0; a7=0; s0=1; s1=0; s2=0;
  #10 a0=0; a1=0; a2=0; a3=0; a4=0; a5=0; a6=0; a7=0; s0=1; s1=0; s2=1;
  #10 a0=0; a1=0; a2=0; a3=0; a4=0; a5=0; a6=0; a7=0; s0=1; s1=1; s2=0;
  #10 a0=0; a1=0; a2=0; a3=0; a4=0; a5=0; a6=0; a7=0; s0=1; s1=1; s2=1;
  #10 a0=0; a1=0; a2=0; a3=0; a4=0; a5=0; a6=0; a7=1; s0=0; s1=0; s2=0;
  #10 a0=0; a1=0; a2=0; a3=0; a4=0; a5=0; a6=0; a7=1; s0=0; s1=0; s2=1;
  #10 a0=0; a1=0; a2=0; a3=0; a4=0; a5=0; a6=0; a7=1; s0=0; s1=1; s2=0;
  #10 a0=0; a1=0; a2=0; a3=0; a4=0; a5=0; a6=0; a7=1; s0=0; s1=1; s2=1;
  #10 a0=0; a1=0; a2=0; a3=0; a4=0; a5=0; a6=0; a7=1; s0=1; s1=0; s2=0;
  #10 a0=0; a1=0; a2=0; a3=0; a4=0; a5=0; a6=0; a7=1; s0=1; s1=0; s2=1;
  #10 a0=0; a1=0; a2=0; a3=0; a4=0; a5=0; a6=0; a7=1; s0=1; s1=1; s2=0;
  #10 a0=0; a1=0; a2=0; a3=0; a4=0; a5=0; a6
=0; a7=1; s0=1; s1=1; s2=1;
  #10 $finish;

end

endmodule

mux8/mux8_tb.vcd
$date
	Sat Sep  9 10:35:16 2023
$end
$version
	Icarus Verilog
$end
$timescale
	1ps
$end
$scope module mux8_tb $end
$var wire 1 ! y $end
$var reg 1 " a0 $end
$var reg 1 # a1 $end
$var reg 1 $ a2 $end
$var reg 1 % a3 $end
$var reg 1 & a4 $end
$var reg 1 ' a5 $end
$var reg 1 ( a6 $end
$var reg 1 ) a7 $end
$var reg 1 * s0 $end
$var reg 1 + s1 $end
$var reg 1 , s2 $end
$scope module m0 $end
$var wire 1 " a0 $end
$var wire 1 # a1 $end
$var wire 1 $ a2 $end
$var wire 1 % a3 $end
$var wire 1 & a4 $end
$var wire 1 ' a5 $end
$var wire 1 ( a6 $end
$var wire 1 ) a7 $end
$var wire 1 * s0 $end
$var wire 1 + s1 $end
$var wire 1 , s2 $end
$var wire 1 ! y $end
$var wire 1 - w6 $end
$var wire 1 . w5 $end
$var wire 1 / w4 $end
$var wire 1 0 w3 $end
$var wire 1 1 w2 $end
$var wire 1 2 w1 $end
$scope module m0 $end
$var wire 1 " a0 $end
$var wire 1 # a1 $end
$var wire 1 * s $end
$var reg 1 2 y $end
$upscope $end
$scope module m1 $end
$var wire 1 $ a0 $end
$var wire 1 % a1 $end
$var wire 1 * s $end
$var reg 1 1 y $end
$upscope $end
$scope module m2 $end
$var wire 1 & a0 $end
$var wire 1 ' a1 $end
$var wire 1 * s $end
$var reg 1 0 y $end
$upscope $end
$scope module m3 $end
$var wire 1 ( a0 $end
$var wire 1 ) a1 $end
$var wire 1 * s $end
$var reg 1 / y $end
$upscope $end
$scope module m4 $end
$var wire 1 2 a0 $end
$var wire 1 1 a1 $end
$var wire 1 + s $end
$var reg 1 . y $end
$upscope $end
$scope module m5 $end
$var wire 1 0 a0 $end
$var wire 1 / a1 $end
$var wire 1 + s $end
$var reg 1 - y $end
$upscope $end
$scope module m6 $end
$var wire 1 . a0 $end
$var wire 1 - a1 $end
$var wire 1 , s $end
$var reg 1 ! y $end
$upscope $end
$upscope $end
$upscope $end
$enddefinitions $end
$comment Show the parameter values. $end
$dumpall
$end
#0
$dumpvars
02
01
00
0/
0.
0-
0,
0+
0*
0)
0(
0'
0&
0%
0$
0#
0"
0!
$end
#20000
1,
#30000
0,
1+
#40000
1,
#50000
0,
0+
1*
#60000
1,
#70000
0,
1+
#80000
1,
#90000
0,
0+
0*
1)
#100000
1,
#110000
0,
1+
#120000
1,
#130000
1/
0,
0+
1*
#140000
1,
#150000
1-
0,
1+
#160000
1!
1,
