mux2/mux2.v
`timescale 1ns/1ps

module mux2(a0,a1,s,y);

input s, a0, a1;
output y;
reg y;


always @ (a0 or a1 or s) begin
  case (s)
    1'b0: y = a0;
    1'b1: y = a1;
  endcase
end
endmodule

mux8/mux8.v
`include "../mux2/mux2.v"
`timescale 1ns / 1ps


module mux8(a0,a1,a2,a3,a4,a5,a6,a7,s0,s1,s2,y);
input a0,a1,a2,a3,a4,a5,a6,a7,s0,s1,s2;
output y;
wire w1,w2,w3,w4,w5,w6;

mux2 m0(a0,a1,s0,w1);
mux2 m1(a2,a3,s0,w2);
mux2 m2(a4,a5,s0,w3);
mux2 m3(a6,a7,s0,w4);

mux2 m4(w1,w2,s1,w5);
mux2 m5(w3,w4,s1,w6);

mux2 m6(w5,w6,s2,y);

endmodule

mux16/mux16.v
`include "../mux8/mux8.v"
`timescale 1ns / 1ps

module mux16 (a0,a1,a2,a3,a4,a5,a6,a7,a8,a9,a10,a11,a12,a13,a14,a15,s0,s1,s2,s3,y);

input a0,a1,a2,a3,a4,a5,a6,a7,a8,a9,a10,a11,a12,a13,a14,a15,s0,s1,s2,s3;
output y;
wire w1,w2;


mux2 m2(w1,w2,s3,y);
mux8 m0(a0,a1,a2,a3,a4,a5,a6,a7,s0,s1,s2,w1);
mux8 m1(a8,a9,a10,a11,a12,a13,a14,a15,s0,s1,s2,w2);


endmodule

mux16/mux16_tb.v
`timescale 1ns / 1ns

module mux16_tb();

    reg d0,d1,d2,d3,d4,d5,d6,d7,d8,d9,d10,d11,d12,d13,d14,d15,s0,s1,s2,s3;
    wire y;
    
    mux16 mux16_1_instance (.a0(d0),.a1(d1),.a2(d2),.a3(d3),.a4(d4),.a5(d5),
    .a6(d6),.a7(d7),.a8(d8),.a9(d9),.a10(d10),.a11(d11),.a12(d12),.a13(d13),.a14(d14),
    .a15(d15),.s0(s0),.s1(s1),.s2(s2),.s3(s3),.y(y));
    initial begin
          $dumpfile("mux16_tb.vcd");
          $dumpvars(0,mux16_tb);

        d0=0;d1=1;d2=0;d3=1;d4=0;d5=1;d6=0;d7=1;d8=0;d9=1;d10=0;d11=1;d12=0;d13=1;d14=0;d15=1;s3=0;s2=0;s1=0;s0=0;
        #1 d0=0;d1=1;d2=0;d3=1;d4=0;d5=1;d6=0;d7=1;d8=0;d9=1;d10=0;d11=1;d12=0;d13=1;d14=0;d15=1;s3=0;s2=0;s1=0;s0=1;
        #1 d0=0;d1=1;d2=0;d3=1;d4=0;d5=1;d6=0;d7=1;d8=0;d9=1;d10=0;d11=1;d12=0;d13=1;d14=0;d15=1;s3=0;s2=0;s1=1;s0=0;
        #1 d0=0;d1=1;d2=0;d3=1;d4=0;d5=1;d6=0;d7=1;d8=0;d9=1;d10=0;d11=1;d12=0;d13=1;d14=0;d15=1;s3=0;s2=0;s1=1;s0=1;
        #1 d0=0;d1=1;d2=0;d3=1;d4=0;d5=1;d6=0;d7=1;d8=0;d9=1;d10=0;d11=1;d12=0;d13=1;d14=0;d15=1;s3=0;s2=1;s1=0;s0=0;
        #1 d0=0;d1=1;d2=0;d3=1;d4=0;d5=1;d6=0;d7=1;d8=0;d9=1;d10=0;d11=1;d12=0;d13=1;d14=0;d15=1;s3=0;s2=1;s1=0;s0=1;
        #1 d0=0;d1=1;d2=0;d3=1;d4=0;d5=1;d6=0;d7=1;d8=0;d9=1;d10=0;d11=1;d12=0;d13=1;d14=0;d15=1;s3=0;s2=1;s1=1;s0=0;
        #1 d0=0;d1=1;d2=0;d3=1;d4=0;d5=1;d6=0;d7=1;d8=0;d9=1;d10=0;d11=1;d12=0;d13=1;d14=0;d15=1;s3=0;s2=1;s1=1;s0=1;
        #1 d0=0;d1=1;d2=0;d3=1;d4=0;d5=1;d6=0;d7=1;d8=0;d9=1;d10=0;d11=1;d12=0;d13=1;d14=0;d15=1;s3=1;s2=0;s1=0;s0=0;
        #1 d0=0;d1=1;d2=0;d3=1;d4=0;d5=1;d6=0;d7=1;d8=0;d9=1;d10=0;d11=1;d12=0;d13=1;d14=0;d15=1;s3=1;s2=0;s1=0;s0=1;
        #1 d0=0;d1=1;d2=0;d3=1;d4=0;d5=1;d6=0;d7=1;d8=0;d9=1;d10=0;d11=1;d12=0;d13=1;d14=0;d15=1;s3=1;s2=0;s1=1;s0=0;
        #1 d0=0;d1=1;d2=0;d3=1;d4=0;d5=1;d6=0;d7=1;d8=0;d9=1;d10=0;d11=1;d12=0;d13=1;d14=0;d15=1;s3=1;s2=0;s1=1;s0=1;
        #1 d0=0;d1=1;d2=0;d3=1;d4=0;d5=1;d6=0;d7=1;d8=0;d9=1;d10=0;d11=1;d12=0;d13=1;d14=0;d15=1;s3=1;s2=1;s1=0;s0=0;
        #1 d0=0;d1=1;d2=0;d3=1;d4=0;d5=1;d6=0;d7=1;d8=0;d9=1;d10=0;d11=1;d12=0;d13=1;d14=0;d15=1;s3=1;s2=1;s1=0;s0=1;
        #1 d0=0;d1=1;d2=0;d3=1;d4=0;d5=1;d6=0;d7=1;d8=0;d9=1;d10=0;d11=1;d12=0;d13=1;d14=0;d15=1;s3=1;s2=1;s1=1;s0=0;
        #1 d0=0;d1=1;d2=0;d3=1;d4=0;d5=1;d6=0;d7=1;d8=0;d9=1;d10=0;d11=1;d12=0;d13=1;d14=0;d15=1;s3=1;s2=1;s1=1;s0=1;
        #1 $finish;
    end
    
    
    initial begin
        $monitor("%b%b%b%b = %b", s3,s2,s1,s0,y);
    end

endmodule

mux16/mux16_tb.vcd
$date
	Sat Sep  9 10:59:31 2023
$end
$version
	Icarus Verilog
$end
$timescale
	1ps
$end
$scope module mux16_tb $end
$var wire 1 ! y $end
$var reg 1 " d0 $end
$var reg 1 # d1 $end
$var reg 1 $ d10 $end
$var reg 1 % d11 $end
$var reg 1 & d12 $end
$var reg 1 ' d13 $end
$var reg 1 ( d14 $end
$var reg 1 ) d15 $end
$var reg 1 * d2 $end
$var reg 1 + d3 $end
$var reg 1 , d4 $end
$var reg 1 - d5 $end
$var reg 1 . d6 $end
$var reg 1 / d7 $end
$var reg 1 0 d8 $end
$var reg 1 1 d9 $end
$var reg 1 2 s0 $end
$var reg 1 3 s1 $end
$var reg 1 4 s2 $end
$var reg 1 5 s3 $end
$scope module mux16_1_instance $end
$var wire 1 " a0 $end
$var wire 1 # a1 $end
$var wire 1 $ a10 $end
$var wire 1 % a11 $end
$var wire 1 & a12 $end
$var wire 1 ' a13 $end
$var wire 1 ( a14 $end
$var wire 1 ) a15 $end
$var wire 1 * a2 $end
$var wire 1 + a3 $end
$var wire 1 , a4 $end
$var wire 1 - a5 $end
$var wire 1 . a6 $end
$var wire 1 / a7 $end
$var wire 1 0 a8 $end
$var wire 1 1 a9 $end
$var wire 1 2 s0 $end
$var wire 1 3 s1 $end
$var wire 1 4 s2 $end
$var wire 1 5 s3 $end
$var wire 1 ! y $end
$var wire 1 6 w2 $end
$var wire 1 7 w1 $end
$scope module m0 $end
$var wire 1 " a0 $end
$var wire 1 # a1 $end
$var wire 1 * a2 $end
$var wire 1 + a3 $end
$var wire 1 , a4 $end
$var wire 1 - a5 $end
$var wire 1 . a6 $end
$var wire 1 / a7 $end
$var wire 1 2 s0 $end
$var wire 1 3 s1 $end
$var wire 1 4 s2 $end
$var wire 1 7 y $end
$var wire 1 8 w6 $end
$var wire 1 9 w5 $end
$var wire 1 : w4 $end
$var wire 1 ; w3 $end
$var wire 1 < w2 $end
$var wire 1 = w1 $end
$scope module m0 $end
$var wire 1 " a0 $end
$var wire 1 # a1 $end
$var wire 1 2 s $end
$var reg 1 = y $end
$upscope $end
$scope module m1 $end
$var wire 1 * a0 $end
$var wire 1 + a1 $end
$var wire 1 2 s $end
$var reg 1 < y $end
$upscope $end
$scope module m2 $end
$var wire 1 , a0 $end
$var wire 1 - a1 $end
$var wire 1 2 s $end
$var reg 1 ; y $end
$upscope $end
$scope module m3 $end
$var wire 1 . a0 $end
$var wire 1 / a1 $end
$var wire 1 2 s $end
$var reg 1 : y $end
$upscope $end
$scope module m4 $end
$var wire 1 = a0 $end
$var wire 1 < a1 $end
$var wire 1 3 s $end
$var reg 1 9 y $end
$upscope $end
$scope module m5 $end
$var wire 1 ; a0 $end
$var wire 1 : a1 $end
$var wire 1 3 s $end
$var reg 1 8 y $end
$upscope $end
$scope module m6 $end
$var wire 1 9 a0 $end
$var wire 1 8 a1 $end
$var wire 1 4 s $end
$var reg 1 7 y $end
$upscope $end
$upscope $end
$scope module m1 $end
$var wire 1 0 a0 $end
$var wire 1 1 a1 $end
$var wire 1 $ a2 $end
$var wire 1 % a3 $end
$var wire 1 & a4 $end
$var wire 1 ' a5 $end
$var wire 1 ( a6 $end
$var wire 1 ) a7 $end
$var wire 1 2 s0 $end
$var wire 1 3 s1 $end
$var wire 1 4 s2 $end
$var wire 1 6 y $end
$var wire 1 > w6 $end
$var wire 1 ? w5 $end
$var wire 1 @ w4 $end
$var wire 1 A w3 $end
$var wire 1 B w2 $end
$var wire 1 C w1 $end
$scope module m0 $end
$var wire 1 0 a0 $end
$var wire 1 1 a1 $end
$var wire 1 2 s $end
$var reg 1 C y $end
$upscope $end
$scope module m1 $end
$var wire 1 $ a0 $end
$var wire 1 % a1 $end
$var wire 1 2 s $end
$var reg 1 B y $end
$upscope $end
$scope module m2 $end
$var wire 1 & a0 $end
$var wire 1 ' a1 $end
$var wire 1 2 s $end
$var reg 1 A y $end
$upscope $end
$scope module m3 $end
$var wire 1 ( a0 $end
$var wire 1 ) a1 $end
$var wire 1 2 s $end
$var reg 1 @ y $end
$upscope $end
$scope module m4 $end
$var wire 1 C a0 $end
$var wire 1 B a1 $end
$var wire 1 3 s $end
$var reg 1 ? y $end
$upscope $end
$scope module m5 $end
$var wire 1 A a0 $end
$var wire 1 @ a1 $end
$var wire 1 3 s $end
$var reg 1 > y $end
$upscope $end
$scope module m6 $end
$var wire 1 ? a0 $end
$var wire 1 > a1 $end
$var wire 1 4 s $end
$var reg 1 6 y $end
$upscope $end
$upscope $end
$scope module m2 $end
$var wire 1 7 a0 $end
$var wire 1 6 a1 $end
$var wire 1 5 s $end
$var reg 1 ! y $end
$upscope $end
$upscope $end
$upscope $end
$enddefinitions $end
$comment Show the parameter values. $end
$dumpall
$end
#0
$dumpvars
0C
0B
0A
0@
0?
0>
0=
0<
0;
0:
09
08
07
06
05
04
03
02
11
00
1/
0.
1-
0,
1+
0*
1)
0(
1'
0&
1%
0$
1#
0"
0!
$end
#1000
1!
17
16
19
18
1?
1>
1=
1<
1;
1:
1C
1B
1A
1@
12
#2000
0!
07
06
09
08
0?
0>
0=
0<
0;
0:
0C
0B
0A
0@
02
13
#3000
1!
17
16
19
18
1?
1>
1=
1<
1;
1:
1C
1B
1A
1@
12
#4000
0!
07
06
09
08
0?
0>
0=
0<
0;
0:
0C
0B
0A
0@
02
03
14
#5000
1!
17
16
19
18
1?
1>
1=
1<
1;
1:
1C
1B
1A
1@
12
#6000
0!
07
06
09
08
0?
0>
0=
0<
0;
0:
0C
0B
0A
0@
02
13
#7000
1!
17
16
19
18
1?
1>
1=
1<
1;
1:
1C
1B
1A
1@
12
#8000
0!
07
06
09
08
0?
0>
0=
0<
0;
0:
0C
0B
0A
0@
02
03
04
15
#9000
1!
17
16
19
18
1?
1>
1=
1<
1;
1:
1C
1B
1A
1@
12
#10000
0!
07
06
09
08
0?
0>
0=
0<
0;
0:
0C
0B
0A
0@
02
13
#11000
1!
17
16
19
18
1?
1>
1=
1<
1;
1:
1C
1B
1A
1@
12
#12000
0!
07
06
09
08
0?
0>
0=
0<
0;
0:
0C
0B
0A
0@
02
03
14
#13000
1!
17
16
19
18
1?
1>
1=
1<
1;
1:
1C
1B
1A
1@
12
#14000
0!
07
06
09
08
0?
0>
0=
0<
0;
0:
0C
0B
0A
0@
02
13
#15000
1!
17
16
19
18
1?
1>
1=
1<
1;
1:
1C
1B
1A
1@
12
